televlc/__init__.py
televlc/televlc.py
televlc-0.2.dist-info/LICENSE.txt
televlc-0.2.dist-info/METADATA
televlc-0.2.dist-info/WHEEL
televlc-0.2.dist-info/top_level.txt
televlc-0.2.dist-info/RECORD
