Metadata-Version: 2.1
Name: televlc
Version: 0.2
Summary: Control VLC media player via telnet from Python
Home-page: https://github.com/RomeroCarranzaEmiliano/televlc
Author: Emiliano Romero Carranza
Author-email: romerocarranzaemiliano@gmail.com
License: UNKNOWN
Keywords: Telnet,VLC,Videolan
Platform: UNKNOWN
